Workbook

Sheet BOQ Estimate
A1: RCC COLUMN / STRUCTURAL ALTERATION – LABOUR & MATERIAL COST ESTIMATE
A2: Indicative budget for Nashik, Maharashtra | INR | Based on photo and limited information; not a structural design or contractor quotation
A4: Sr. | B4: Stage / Work Description | C4: Material / Equipment Allowance (₹) | D4: Labour / Professional Fee (₹) | E4: Other / Disposal (₹) | F4: Low Total (₹) | G4: High Total (₹) | H4: Notes / Assumptions
A5: 1 | B5: Structural engineer site inspection, measurements, review of available drawings | C5: 0 | D5: 5000 | E5: 0 | F5: =C5+D5+E5 | G5: =C5+D5+E5 | H5: Written site assessment required
A6: 2 | B6: Structural calculations, feasibility and written strengthening / load-transfer design | C6: 0 | D6: 15000 | E6: 0 | F6: =C6+D6+E6 | G6: =C6+D6+E6 | H6: Fee varies with complexity
A7: 3 | B7: Temporary shoring / propping system: hire, base plates, bracing and installation materials | C7: 12000 | D7: 8000 | E7: 0 | F7: =C7+D7+E7 | G7: =C7+D7+E7 | H7: Engineer to specify; may need support through lower floors
A8: 4 | B8: Site barricading, floor/wall protection, dust control and PPE | C8: 4000 | D8: 2500 | E8: 0 | F8: =C8+D8+E8 | G8: =C8+D8+E8 | H8: Masks, eye/ear protection, sheets, barriers
A9: 5 | B9: Controlled concrete/steel cutting and demolition equipment allowance | C9: 8000 | D9: 10000 | E9: 0 | F9: =C9+D9+E9 | G9: =C9+D9+E9 | H9: Only if engineer approves; no DIY cutting
A10: 6 | B10: Skilled demolition / structural crew allowance | C10: 0 | D10: 12000 | E10: 0 | F10: =C10+D10+E10 | G10: =C10+D10+E10 | H10: Crew/day allowance; actual duration site-dependent
A11: 7 | B11: Debris loading, carrying and disposal | C11: 0 | D11: 3500 | E11: 4500 | F11: =C11+D11+E11 | G11: =C11+D11+E11 | H11: Access and quantity affect price
A12: 8 | B12: Electrical inspection, isolation and minor wire relocation allowance | C12: 2000 | D12: 2500 | E12: 0 | F12: =C12+D12+E12 | G12: =C12+D12+E12 | H12: Electrician to verify before work
A13: 9 | B13: Minor patching: mortar, repair compound, mesh, plaster and corner beads | C13: 5000 | D13: 5000 | E13: 0 | F13: =C13+D13+E13 | G13: =C13+D13+E13 | H13: Only for local surface reinstatement
A14: 10 | B14: Primer, paint and finishing of affected wall/ceiling areas | C14: 3500 | D14: 3000 | E14: 0 | F14: =C14+D14+E14 | G14: =C14+D14+E14 | H14: Area-dependent
A15: 11 | B15: Post-work engineer inspection / completion note | C15: 0 | D15: 5000 | E15: 0 | F15: =C15+D15+E15 | G15: =C15+D15+E15 | H15: Before removing temporary supports
B16: OPTIONAL / SITE-SPECIFIC: Structural steel transfer beam, connections, new supports/foundation and installation | C16: TBD after design | D16: TBD after design | F16: NOT INCLUDED | G16: NOT INCLUDED | H16: Potentially the largest cost; engineer's design and measured quantities required.
B18: Base estimate subtotal (excludes major transfer beam / new foundations) | F18: =SUM(F5:F15) | G18: =SUM(G5:G15)
B19: Contingency allowance (15%) | F19: =F18*15% | G19: =G18*15%
B20: Indicative base total including contingency | F20: =F18+F19 | G20: =G18+G19
A22: IMPORTANT: The above line-item allowances are preliminary placeholders. Replace with engineer/contractor quotations after a site visit.
A24: • Safety: Photo shows ceiling/plaster distress and visible beam-like members; it cannot confirm the structural system or whether the column can be removed.
A25: • Do not remove or cut an RCC column, beam, reinforcement, or connected member until a qualified structural engineer has inspected the site and issued a signed design/method statement.
A26: • If a transfer beam, steel frame, new columns or foundations are required, obtain a separate engineered BOQ. These major structural works are deliberately excluded from the base total.
A27: • Estimate assumes a small work area and ordinary access. Taxes, permissions, extensive electrical work, hidden damage, night work, and major structural replacement are excluded.
A28: • Temporary supports must be designed and installed under engineer supervision; do not assume one floor's props are enough. Consider the load path through floors below.

Sheet Summary
A1: COST SUMMARY
A3: Category | B3: Low Estimate (₹) | C3: High Estimate (₹)
A4: Materials / equipment allowances | B4: =SUM('BOQ Estimate'!C5:C15) | C4: =SUM('BOQ Estimate'!C5:C15)
A5: Labour / professional fees | B5: =SUM('BOQ Estimate'!D5:D15) | C5: =SUM('BOQ Estimate'!D5:D15)
A6: Other / disposal | B6: =SUM('BOQ Estimate'!E5:E15) | C6: =SUM('BOQ Estimate'!E5:E15)
A7: Base subtotal | B7: ='BOQ Estimate'!F18 | C7: ='BOQ Estimate'!G18
A8: Contingency 15% | B8: ='BOQ Estimate'!F19 | C8: ='BOQ Estimate'!G19
A9: Base total (major structural transfer work excluded) | B9: ='BOQ Estimate'!F20 | C9: ='BOQ Estimate'!G20
A10: Major structural steel / new supports / foundations | B10: TBD after design | C10: TBD after design
